testeasydubins/__init__.py
testeasydubins/__main__.py
testeasydubins/config.cfg
testeasydubins/dubin_path.py
testeasydubins-1.1.0.dist-info/LICENSE
testeasydubins-1.1.0.dist-info/METADATA
testeasydubins-1.1.0.dist-info/WHEEL
testeasydubins-1.1.0.dist-info/entry_points.txt
testeasydubins-1.1.0.dist-info/top_level.txt
testeasydubins-1.1.0.dist-info/RECORD
