Metadata-Version: 2.1
Name: testeasydubins
Version: 1.1.0
Summary: To generate dubin curves projection points.
Home-page: https://github.com/rsrishav/easydubins
Author: Rishav
Author-email: xyz@gmail.com
License: GPL3
Platform: UNKNOWN
Classifier: Programming Language :: Python
Classifier: Programming Language :: Python :: 2
Classifier: Programming Language :: Python :: 3
Classifier: Operating System :: OS Independent
Requires-Dist: importlib-resources
